commondao/__init__.py
commondao/__main__.py
commondao/codegen.py
commondao/index.py
commondao/mapper.py
commondao/py.typed
commondao/utils/__init__.py
commondao/utils/common.py
commondao/utils/grammar.py
commondao/utils/templates.py
commondao/utils/wordstyle.py
lessweb_commondao-1.1.0.dist-info/LICENSE.txt
lessweb_commondao-1.1.0.dist-info/METADATA
lessweb_commondao-1.1.0.dist-info/WHEEL
lessweb_commondao-1.1.0.dist-info/entry_points.txt
lessweb_commondao-1.1.0.dist-info/top_level.txt
lessweb_commondao-1.1.0.dist-info/RECORD
