Metadata-Version: 2.1
Name: lessweb-commondao
Version: 1.1.0
Summary: Mysql service and toolkit for lessweb
Author-email: qorzj <goodhorsezxj@gmail.com>
License: Apache 2
Keywords: lessweb,mysql
Requires-Python: >=3.7
License-File: LICENSE.txt
Requires-Dist: aiohttp
Requires-Dist: lesscli
Requires-Dist: lessweb
Requires-Dist: mysql-connector
Requires-Dist: aiomysql
